bstools/__init__.py
bstools/bsNetwork.py
bstools/bsPrint.py
bstools/bsSsh.py
bstools/bsTime.py
bstools-0.1.23.dist-info/LICENSE
bstools-0.1.23.dist-info/METADATA
bstools-0.1.23.dist-info/WHEEL
bstools-0.1.23.dist-info/top_level.txt
bstools-0.1.23.dist-info/RECORD
