Metadata-Version: 2.1
Name: bstools
Version: 0.1.23
Summary: some very useful tools
Home-page: http://www.swfu.co/
Author: Bernie Suen
Author-email: bernie.suen@outlook.com
License: UNKNOWN
Project-URL: Documentation, https://github.com/qkjs/bstools/wiki
Project-URL: Code, https://github.com/qkjs/bstools
Project-URL: Issue tracker, https://github.com/qkjs/bstools/issues
Platform: UNKNOWN
Classifier: Development Status :: 4 - Beta
Classifier: Programming Language :: Python :: 3
Classifier: Programming Language :: Python :: 2.7
Classifier: License :: OSI Approved :: MIT License
Classifier: Operating System :: OS Independent
Requires-Dist: paramiko
